ingest_data.py
main.py
score.py
train.py
house_price_prediction-0.0.1.dist-info/METADATA
house_price_prediction-0.0.1.dist-info/WHEEL
house_price_prediction-0.0.1.dist-info/top_level.txt
house_price_prediction-0.0.1.dist-info/RECORD
